Metadata-Version: 2.1
Name: selectable-text
Version: 0.0.1
Summary: Project Description
Home-page: UNKNOWN
Author: John Lithio <jlithio@gmail.com>
License: MIT
Platform: UNKNOWN
Classifier: Framework :: Dash
License-File: LICENSE
